{
  "project_info": {
    "project_number": "221243565694",
    "project_id": "friendlink-62eae",
    "storage_bucket": "friendlink-62eae.appspot.com"
  },
  "client": [
    {
      "client_info": {
        "mobilesdk_app_id": "1:221243565694:android:65fb016488b0578f2bda2f",
        "android_client_info": {
          "package_name": "com.skr.android.friendlink"
        }
      },
      "oauth_client": [
        {
          "client_id": "221243565694-k0h44k4gb33q94sv9ra7ubohfil25pqh.apps.googleusercontent.com",
          "client_type": 3
        }
      ],
      "api_key": [
        {
          "current_key": "AIzaSyDwQzs1X-9gGu_Mbp-7f7gnsWRoNasRTNU"
        }
      ],
      "services": {
        "appinvite_service": {
          "other_platform_oauth_client": [
            {
              "client_id": "221243565694-k0h44k4gb33q94sv9ra7ubohfil25pqh.apps.googleusercontent.com",
              "client_type": 3
            }
          ]
        }
      }
    }
  ],
  "configuration_version": "1"
}